translate_docx/__init__.py
translate_docx/cli.py
translate_docx/extractor.py
translate_docx/models.py
translate_docx/rebuilder.py
translate_docx/translator.py
translate_docx/utils.py
translate_docx-2026.1.13rc2.dist-info/METADATA
translate_docx-2026.1.13rc2.dist-info/WHEEL
translate_docx-2026.1.13rc2.dist-info/entry_points.txt
translate_docx-2026.1.13rc2.dist-info/licenses/LICENSE
translate_docx-2026.1.13rc2.dist-info/RECORD
