Metadata-Version: 2.4
Name: translate-docx
Version: 2026.1.13rc2
Summary: Translate .docx files      while preserving all text formatting
Project-URL: Homepage, https://github.com/pixelprotest/translate-docx
Project-URL: Bug Tracker, https://github.com/pixelprotest/translate-docx/issues
Project-URL: Documentation, https://github.com/pixelprotest/translate-docx#readme
Author-email: pixelprotest <hello@pixelprotest.com>
License: MIT
License-File: LICENSE
Keywords: document,docx,formatting,translation,word
Classifier: Development Status :: 4 - Beta
Classifier: Intended Audience :: Developers
Classifier: License :: OSI Approved :: MIT License
Classifier: Operating System :: OS Independent
Classifier: Programming Language :: Python :: 3
Classifier: Programming Language :: Python :: 3.13
Classifier: Programming Language :: Python :: 3.14
Classifier: Topic :: Office/Business
Classifier: Topic :: Text Processing :: Linguistic
Requires-Python: >=3.13
Requires-Dist: deep-translator[docx]>=1.11.4
Requires-Dist: python-docx>=0.8.11
Requires-Dist: typer>=0.9.0
